<annotation>
	<folder>collectedimages</folder>
	<filename>LetterG.22be7e49-a9ac-11ec-984d-54bf643bdae7.jpg</filename>
	<path>D:\RealTimeObjectDetection-main\RealTimeObjectDetection-main\Tensorflow\workspace\images\collectedimages\LetterG.22be7e49-a9ac-11ec-984d-54bf643bdae7.jpg</path>
	<source>
		<database>Unknown</database>
	</source>
	<size>
		<width>640</width>
		<height>480</height>
		<depth>3</depth>
	</size>
	<segmented>0</segmented>
	<object>
		<name>LetterG</name>
		<pose>Unspecified</pose>
		<truncated>0</truncated>
		<difficult>0</difficult>
		<bndbox>
			<xmin>235</xmin>
			<ymin>205</ymin>
			<xmax>412</xmax>
			<ymax>297</ymax>
		</bndbox>
	</object>
</annotation>
